{"auxiliaryData":{},"parameters":{"batchSize":"20","hashSize":"1000","internalIterationsNumber":"100","partiesFile":"Parties.txt","partyID":"0","processId":"0","protocolName":"ObliviousDictionary","reportStatistics":"1","tool":"poly","version":"3Tables"},"times":[{"iteration_0":"2.740","iteration_1":"3.472","iteration_10":"15.091","iteration_11":"2.661","iteration_12":"1.971","iteration_13":"2.702","iteration_14":"2.606","iteration_15":"2.091","iteration_16":"2.537","iteration_17":"2.828","iteration_18":"2.930","iteration_19":"3.202","iteration_2":"3.537","iteration_20":"4.188","iteration_21":"3.202","iteration_22":"4.193","iteration_23":"4.063","iteration_24":"4.099","iteration_25":"3.954","iteration_26":"4.039","iteration_27":"3.900","iteration_28":"3.151","iteration_29":"3.985","iteration_3":"2.783","iteration_30":"5.478","iteration_31":"3.871","iteration_32":"3.913","iteration_33":"3.200","iteration_34":"3.845","iteration_35":"3.750","iteration_36":"3.404","iteration_37":"3.918","iteration_38":"3.715","iteration_39":"3.426","iteration_4":"2.763","iteration_40":"2.452","iteration_41":"3.107","iteration_42":"3.205","iteration_43":"3.478","iteration_44":"3.961","iteration_45":"3.937","iteration_46":"3.947","iteration_47":"3.910","iteration_48":"3.804","iteration_49":"3.787","iteration_5":"3.686","iteration_50":"3.886","iteration_51":"3.374","iteration_52":"3.883","iteration_53":"5.512","iteration_54":"7.381","iteration_55":"4.381","iteration_56":"3.407","iteration_57":"2.715","iteration_58":"3.560","iteration_59":"3.454","iteration_6":"3.668","iteration_60":"3.129","iteration_61":"2.699","iteration_62":"2.654","iteration_63":"3.419","iteration_64":"2.841","iteration_65":"3.583","iteration_66":"2.700","iteration_67":"2.777","iteration_68":"3.413","iteration_69":"3.372","iteration_7":"3.684","iteration_70":"3.001","iteration_71":"3.576","iteration_72":"3.262","iteration_73":"3.346","iteration_74":"3.449","iteration_75":"2.649","iteration_76":"3.494","iteration_77":"3.439","iteration_78":"3.375","iteration_79":"2.955","iteration_8":"4.211","iteration_80":"3.605","iteration_81":"3.427","iteration_82":"2.623","iteration_83":"3.529","iteration_84":"2.760","iteration_85":"3.988","iteration_86":"3.594","iteration_87":"3.555","iteration_88":"3.728","iteration_89":"3.836","iteration_9":"4.093","iteration_90":"3.551","iteration_91":"3.658","iteration_92":"3.433","iteration_93":"3.818","iteration_94":"3.462","iteration_95":"3.765","iteration_96":"3.613","iteration_97":"4.182","iteration_98":"2.885","iteration_99":"2.887","name":"Online"}]}